model_assessment/__init__.py
model_assessment/performance.py
pybuc/__init__.py
pybuc/buc.py
pybuc-0.56.2.dist-info/licenses/LICENSE.txt
statespace/__init__.py
statespace/durbin_koopman_smoother.py
statespace/kalman_filter.py
utils/__init__.py
utils/array_operations.py
utils/data_transforms.py
vectorized/__init__.py
vectorized/distributions.py
pybuc-0.56.2.dist-info/METADATA
pybuc-0.56.2.dist-info/WHEEL
pybuc-0.56.2.dist-info/top_level.txt
pybuc-0.56.2.dist-info/RECORD
