Metadata-Version: 2.4
Name: pybuc
Version: 0.56.2
Summary: Fast estimation of Bayesian structural time series models via Gibbs sampling.
Author: Devin D. Garcia
License: BSD 3-Clause
Keywords: structural,time series,unobserved components,bsts,forecast,state space
Requires-Python: >=3.10
License-File: LICENSE.txt
Requires-Dist: matplotlib>=3.10.3
Requires-Dist: numba>=0.61.2
Requires-Dist: pandas>=2.2.3
Requires-Dist: seaborn>=0.13.2
Requires-Dist: statsmodels>=0.14.4
Dynamic: license-file
